[
  {
    "round": 0,
    "accuracy": 0.1,
    "loss": 2.302585092994046
  },
  {
    "round": 1,
    "accuracy": 0.0892,
    "loss": 2.3033084869384766
  },
  {
    "round": 2,
    "accuracy": 0.1028,
    "loss": 2.303260564804077
  },
  {
    "round": 3,
    "accuracy": 0.1032,
    "loss": 2.303159713745117
  },
  {
    "round": 4,
    "accuracy": 0.1135,
    "loss": 2.3024566173553467
  },
  {
    "round": 5,
    "accuracy": 0.0974,
    "loss": 2.302617073059082
  },
  {
    "round": 6,
    "accuracy": 0.0958,
    "loss": 2.3028366565704346
  },
  {
    "round": 7,
    "accuracy": 0.101,
    "loss": 2.3027355670928955
  },
  {
    "round": 8,
    "accuracy": 0.1009,
    "loss": 2.3026092052459717
  },
  {
    "round": 9,
    "accuracy": 0.0982,
    "loss": 2.302605390548706
  },
  {
    "round": 10,
    "accuracy": 0.098,
    "loss": 2.3025832176208496
  },
  {
    "round": 11,
    "accuracy": 0.0892,
    "loss": 2.3032994270324707
  },
  {
    "round": 12,
    "accuracy": 0.1028,
    "loss": 2.303246021270752
  },
  {
    "round": 13,
    "accuracy": 0.1032,
    "loss": 2.3031411170959473
  },
  {
    "round": 14,
    "accuracy": 0.1135,
    "loss": 2.3024356365203857
  },
  {
    "round": 15,
    "accuracy": 0.0974,
    "loss": 2.3025951385498047
  },
  {
    "round": 16,
    "accuracy": 0.0958,
    "loss": 2.3028156757354736
  },
  {
    "round": 17,
    "accuracy": 0.101,
    "loss": 2.3027172088623047
  },
  {
    "round": 18,
    "accuracy": 0.1009,
    "loss": 2.3025951385498047
  },
  {
    "round": 19,
    "accuracy": 0.0982,
    "loss": 2.3025970458984375
  },
  {
    "round": 20,
    "accuracy": 0.098,
    "loss": 2.3025825023651123
  },
  {
    "round": 21,
    "accuracy": 0.0892,
    "loss": 2.3032917976379395
  },
  {
    "round": 22,
    "accuracy": 0.1028,
    "loss": 2.3032331466674805
  },
  {
    "round": 23,
    "accuracy": 0.1032,
    "loss": 2.303123712539673
  },
  {
    "round": 24,
    "accuracy": 0.1135,
    "loss": 2.3024168014526367
  },
  {
    "round": 25,
    "accuracy": 0.0974,
    "loss": 2.3025753498077393
  },
  {
    "round": 26,
    "accuracy": 0.0958,
    "loss": 2.3027966022491455
  },
  {
    "round": 27,
    "accuracy": 0.101,
    "loss": 2.3027002811431885
  },
  {
    "round": 28,
    "accuracy": 0.1009,
    "loss": 2.302582263946533
  },
  {
    "round": 29,
    "accuracy": 0.0982,
    "loss": 2.3025894165039062
  },
  {
    "round": 30,
    "accuracy": 0.098,
    "loss": 2.302582263946533
  },
  {
    "round": 31,
    "accuracy": 0.0892,
    "loss": 2.303285598754883
  },
  {
    "round": 32,
    "accuracy": 0.1028,
    "loss": 2.3032212257385254
  },
  {
    "round": 33,
    "accuracy": 0.1032,
    "loss": 2.303107976913452
  },
  {
    "round": 34,
    "accuracy": 0.1135,
    "loss": 2.302399158477783
  },
  {
    "round": 35,
    "accuracy": 0.0974,
    "loss": 2.3025567531585693
  },
  {
    "round": 36,
    "accuracy": 0.0958,
    "loss": 2.302778959274292
  },
  {
    "round": 37,
    "accuracy": 0.101,
    "loss": 2.302685260772705
  },
  {
    "round": 38,
    "accuracy": 0.1009,
    "loss": 2.3025708198547363
  },
  {
    "round": 39,
    "accuracy": 0.0982,
    "loss": 2.3025832176208496
  },
  {
    "round": 40,
    "accuracy": 0.098,
    "loss": 2.302582025527954
  },
  {
    "round": 41,
    "accuracy": 0.0892,
    "loss": 2.3032796382904053
  },
  {
    "round": 42,
    "accuracy": 0.1028,
    "loss": 2.303210973739624
  },
  {
    "round": 43,
    "accuracy": 0.1032,
    "loss": 2.3030941486358643
  },
  {
    "round": 44,
    "accuracy": 0.1135,
    "loss": 2.3023836612701416
  },
  {
    "round": 45,
    "accuracy": 0.0974,
    "loss": 2.3025403022766113
  },
  {
    "round": 46,
    "accuracy": 0.0958,
    "loss": 2.302762985229492
  },
  {
    "round": 47,
    "accuracy": 0.101,
    "loss": 2.302671194076538
  },
  {
    "round": 48,
    "accuracy": 0.1009,
    "loss": 2.302560567855835
  },
  {
    "round": 49,
    "accuracy": 0.0982,
    "loss": 2.3025777339935303
  },
  {
    "round": 50,
    "accuracy": 0.098,
    "loss": 2.3025832176208496
  },
  {
    "round": 51,
    "accuracy": 0.0892,
    "loss": 2.303274631500244
  },
  {
    "round": 52,
    "accuracy": 0.1028,
    "loss": 2.303201198577881
  },
  {
    "round": 53,
    "accuracy": 0.1032,
    "loss": 2.3030805587768555
  },
  {
    "round": 54,
    "accuracy": 0.1135,
    "loss": 2.302368640899658
  },
  {
    "round": 55,
    "accuracy": 0.0974,
    "loss": 2.3025243282318115
  },
  {
    "round": 56,
    "accuracy": 0.0958,
    "loss": 2.302747964859009
  },
  {
    "round": 57,
    "accuracy": 0.101,
    "loss": 2.3026583194732666
  },
  {
    "round": 58,
    "accuracy": 0.1009,
    "loss": 2.30255126953125
  },
  {
    "round": 59,
    "accuracy": 0.0982,
    "loss": 2.302572727203369
  },
  {
    "round": 60,
    "accuracy": 0.098,
    "loss": 2.302583932876587
  },
  {
    "round": 61,
    "accuracy": 0.0892,
    "loss": 2.303269624710083
  },
  {
    "round": 62,
    "accuracy": 0.1028,
    "loss": 2.303191900253296
  },
  {
    "round": 63,
    "accuracy": 0.1032,
    "loss": 2.3030686378479004
  },
  {
    "round": 64,
    "accuracy": 0.1135,
    "loss": 2.302354574203491
  },
  {
    "round": 65,
    "accuracy": 0.0974,
    "loss": 2.3025102615356445
  },
  {
    "round": 66,
    "accuracy": 0.0958,
    "loss": 2.302733898162842
  },
  {
    "round": 67,
    "accuracy": 0.101,
    "loss": 2.3026463985443115
  },
  {
    "round": 68,
    "accuracy": 0.1009,
    "loss": 2.302542209625244
  },
  {
    "round": 69,
    "accuracy": 0.0982,
    "loss": 2.302567958831787
  },
  {
    "round": 70,
    "accuracy": 0.098,
    "loss": 2.302584648132324
  },
  {
    "round": 71,
    "accuracy": 0.0892,
    "loss": 2.303265333175659
  },
  {
    "round": 72,
    "accuracy": 0.1028,
    "loss": 2.3031833171844482
  },
  {
    "round": 73,
    "accuracy": 0.1032,
    "loss": 2.3030569553375244
  },
  {
    "round": 74,
    "accuracy": 0.1135,
    "loss": 2.3023416996002197
  },
  {
    "round": 75,
    "accuracy": 0.0974,
    "loss": 2.3024964332580566
  },
  {
    "round": 76,
    "accuracy": 0.0958,
    "loss": 2.3027212619781494
  },
  {
    "round": 77,
    "accuracy": 0.101,
    "loss": 2.302635669708252
  },
  {
    "round": 78,
    "accuracy": 0.1009,
    "loss": 2.302534341812134
  },
  {
    "round": 79,
    "accuracy": 0.0982,
    "loss": 2.3025643825531006
  },
  {
    "round": 80,
    "accuracy": 0.098,
    "loss": 2.302586317062378
  },
  {
    "round": 81,
    "accuracy": 0.0892,
    "loss": 2.3032617568969727
  },
  {
    "round": 82,
    "accuracy": 0.1028,
    "loss": 2.3031764030456543
  },
  {
    "round": 83,
    "accuracy": 0.1032,
    "loss": 2.3030471801757812
  },
  {
    "round": 84,
    "accuracy": 0.1135,
    "loss": 2.302330493927002
  },
  {
    "round": 85,
    "accuracy": 0.0974,
    "loss": 2.3024847507476807
  },
  {
    "round": 86,
    "accuracy": 0.0958,
    "loss": 2.3027098178863525
  },
  {
    "round": 87,
    "accuracy": 0.101,
    "loss": 2.302626132965088
  },
  {
    "round": 88,
    "accuracy": 0.1009,
    "loss": 2.302527666091919
  },
  {
    "round": 89,
    "accuracy": 0.0982,
    "loss": 2.3025612831115723
  },
  {
    "round": 90,
    "accuracy": 0.098,
    "loss": 2.30258846282959
  },
  {
    "round": 91,
    "accuracy": 0.0892,
    "loss": 2.3032593727111816
  },
  {
    "round": 92,
    "accuracy": 0.1028,
    "loss": 2.3031702041625977
  },
  {
    "round": 93,
    "accuracy": 0.1032,
    "loss": 2.303037643432617
  },
  {
    "round": 94,
    "accuracy": 0.1135,
    "loss": 2.3023200035095215
  },
  {
    "round": 95,
    "accuracy": 0.0974,
    "loss": 2.302473545074463
  },
  {
    "round": 96,
    "accuracy": 0.0958,
    "loss": 2.3026986122131348
  },
  {
    "round": 97,
    "accuracy": 0.101,
    "loss": 2.302617073059082
  },
  {
    "round": 98,
    "accuracy": 0.1009,
    "loss": 2.302521228790283
  },
  {
    "round": 99,
    "accuracy": 0.0982,
    "loss": 2.3025588989257812
  },
  {
    "round": 100,
    "accuracy": 0.098,
    "loss": 2.3025903701782227
  },
  {
    "round": 101,
    "accuracy": 0.0892,
    "loss": 2.303257465362549
  },
  {
    "round": 102,
    "accuracy": 0.1028,
    "loss": 2.303164482116699
  },
  {
    "round": 103,
    "accuracy": 0.1032,
    "loss": 2.303029775619507
  },
  {
    "round": 104,
    "accuracy": 0.1135,
    "loss": 2.3023104667663574
  },
  {
    "round": 105,
    "accuracy": 0.0974,
    "loss": 2.3024630546569824
  },
  {
    "round": 106,
    "accuracy": 0.0958,
    "loss": 2.3026890754699707
  },
  {
    "round": 107,
    "accuracy": 0.101,
    "loss": 2.3026089668273926
  },
  {
    "round": 108,
    "accuracy": 0.1009,
    "loss": 2.302515745162964
  },
  {
    "round": 109,
    "accuracy": 0.0982,
    "loss": 2.3025567531585693
  },
  {
    "round": 110,
    "accuracy": 0.098,
    "loss": 2.3025929927825928
  },
  {
    "round": 111,
    "accuracy": 0.0892,
    "loss": 2.303255319595337
  },
  {
    "round": 112,
    "accuracy": 0.1028,
    "loss": 2.303159475326538
  },
  {
    "round": 113,
    "accuracy": 0.1032,
    "loss": 2.3030223846435547
  },
  {
    "round": 114,
    "accuracy": 0.1135,
    "loss": 2.3023018836975098
  },
  {
    "round": 115,
    "accuracy": 0.0974,
    "loss": 2.3024539947509766
  },
  {
    "round": 116,
    "accuracy": 0.0958,
    "loss": 2.302680730819702
  },
  {
    "round": 117,
    "accuracy": 0.101,
    "loss": 2.3026018142700195
  },
  {
    "round": 118,
    "accuracy": 0.1009,
    "loss": 2.302511215209961
  },
  {
    "round": 119,
    "accuracy": 0.0982,
    "loss": 2.3025550842285156
  },
  {
    "round": 120,
    "accuracy": 0.098,
    "loss": 2.302595376968384
  },
  {
    "round": 121,
    "accuracy": 0.0892,
    "loss": 2.3032543659210205
  },
  {
    "round": 122,
    "accuracy": 0.1028,
    "loss": 2.3031551837921143
  },
  {
    "round": 123,
    "accuracy": 0.1032,
    "loss": 2.3030154705047607
  },
  {
    "round": 124,
    "accuracy": 0.1135,
    "loss": 2.3022937774658203
  },
  {
    "round": 125,
    "accuracy": 0.0974,
    "loss": 2.302445411682129
  },
  {
    "round": 126,
    "accuracy": 0.0958,
    "loss": 2.3026721477508545
  },
  {
    "round": 127,
    "accuracy": 0.101,
    "loss": 2.3025949001312256
  },
  {
    "round": 128,
    "accuracy": 0.1009,
    "loss": 2.3025062084198
  },
  {
    "round": 129,
    "accuracy": 0.0982,
    "loss": 2.302553176879883
  },
  {
    "round": 130,
    "accuracy": 0.098,
    "loss": 2.302597761154175
  },
  {
    "round": 131,
    "accuracy": 0.0892,
    "loss": 2.3032524585723877
  },
  {
    "round": 132,
    "accuracy": 0.1028,
    "loss": 2.3031508922576904
  },
  {
    "round": 133,
    "accuracy": 0.1032,
    "loss": 2.303009033203125
  },
  {
    "round": 134,
    "accuracy": 0.1135,
    "loss": 2.302286148071289
  },
  {
    "round": 135,
    "accuracy": 0.0974,
    "loss": 2.3024377822875977
  },
  {
    "round": 136,
    "accuracy": 0.0958,
    "loss": 2.302664279937744
  },
  {
    "round": 137,
    "accuracy": 0.101,
    "loss": 2.302588701248169
  },
  {
    "round": 138,
    "accuracy": 0.1009,
    "loss": 2.302502393722534
  },
  {
    "round": 139,
    "accuracy": 0.0982,
    "loss": 2.3025522232055664
  },
  {
    "round": 140,
    "accuracy": 0.098,
    "loss": 2.3025999069213867
  },
  {
    "round": 141,
    "accuracy": 0.0892,
    "loss": 2.3032519817352295
  },
  {
    "round": 142,
    "accuracy": 0.1028,
    "loss": 2.3031468391418457
  },
  {
    "round": 143,
    "accuracy": 0.1032,
    "loss": 2.3030030727386475
  },
  {
    "round": 144,
    "accuracy": 0.1135,
    "loss": 2.3022797107696533
  },
  {
    "round": 145,
    "accuracy": 0.0974,
    "loss": 2.3024306297302246
  },
  {
    "round": 146,
    "accuracy": 0.0958,
    "loss": 2.3026578426361084
  },
  {
    "round": 147,
    "accuracy": 0.101,
    "loss": 2.3025832176208496
  },
  {
    "round": 148,
    "accuracy": 0.1009,
    "loss": 2.3024988174438477
  },
  {
    "round": 149,
    "accuracy": 0.0982,
    "loss": 2.30255126953125
  },
  {
    "round": 150,
    "accuracy": 0.098,
    "loss": 2.302603006362915
  },
  {
    "round": 151,
    "accuracy": 0.0892,
    "loss": 2.303251266479492
  },
  {
    "round": 152,
    "accuracy": 0.1028,
    "loss": 2.3031437397003174
  },
  {
    "round": 153,
    "accuracy": 0.1032,
    "loss": 2.3029980659484863
  },
  {
    "round": 154,
    "accuracy": 0.1135,
    "loss": 2.302273750305176
  },
  {
    "round": 155,
    "accuracy": 0.0974,
    "loss": 2.302424192428589
  },
  {
    "round": 156,
    "accuracy": 0.0958,
    "loss": 2.302651882171631
  },
  {
    "round": 157,
    "accuracy": 0.101,
    "loss": 2.3025782108306885
  },
  {
    "round": 158,
    "accuracy": 0.1009,
    "loss": 2.3024961948394775
  },
  {
    "round": 159,
    "accuracy": 0.0982,
    "loss": 2.302551031112671
  },
  {
    "round": 160,
    "accuracy": 0.098,
    "loss": 2.3026058673858643
  },
  {
    "round": 161,
    "accuracy": 0.0892,
    "loss": 2.303251028060913
  },
  {
    "round": 162,
    "accuracy": 0.1028,
    "loss": 2.3031411170959473
  },
  {
    "round": 163,
    "accuracy": 0.1032,
    "loss": 2.3029932975769043
  },
  {
    "round": 164,
    "accuracy": 0.1135,
    "loss": 2.3022677898406982
  },
  {
    "round": 165,
    "accuracy": 0.0974,
    "loss": 2.302417755126953
  },
  {
    "round": 166,
    "accuracy": 0.0958,
    "loss": 2.302645683288574
  },
  {
    "round": 167,
    "accuracy": 0.101,
    "loss": 2.3025739192962646
  },
  {
    "round": 168,
    "accuracy": 0.1009,
    "loss": 2.30249285697937
  },
  {
    "round": 169,
    "accuracy": 0.0982,
    "loss": 2.3025500774383545
  },
  {
    "round": 170,
    "accuracy": 0.098,
    "loss": 2.3026084899902344
  },
  {
    "round": 171,
    "accuracy": 0.0892,
    "loss": 2.303250789642334
  },
  {
    "round": 172,
    "accuracy": 0.1028,
    "loss": 2.303138256072998
  },
  {
    "round": 173,
    "accuracy": 0.1032,
    "loss": 2.3029890060424805
  },
  {
    "round": 174,
    "accuracy": 0.1135,
    "loss": 2.302262306213379
  },
  {
    "round": 175,
    "accuracy": 0.0974,
    "loss": 2.3024120330810547
  },
  {
    "round": 176,
    "accuracy": 0.0958,
    "loss": 2.302639961242676
  },
  {
    "round": 177,
    "accuracy": 0.101,
    "loss": 2.3025693893432617
  },
  {
    "round": 178,
    "accuracy": 0.1009,
    "loss": 2.302490234375
  },
  {
    "round": 179,
    "accuracy": 0.0982,
    "loss": 2.3025498390197754
  },
  {
    "round": 180,
    "accuracy": 0.098,
    "loss": 2.3026108741760254
  },
  {
    "round": 181,
    "accuracy": 0.0892,
    "loss": 2.303250312805176
  },
  {
    "round": 182,
    "accuracy": 0.1028,
    "loss": 2.303135633468628
  },
  {
    "round": 183,
    "accuracy": 0.1032,
    "loss": 2.302985191345215
  },
  {
    "round": 184,
    "accuracy": 0.1135,
    "loss": 2.302257537841797
  },
  {
    "round": 185,
    "accuracy": 0.0974,
    "loss": 2.3024065494537354
  },
  {
    "round": 186,
    "accuracy": 0.0958,
    "loss": 2.302635431289673
  },
  {
    "round": 187,
    "accuracy": 0.101,
    "loss": 2.302565336227417
  },
  {
    "round": 188,
    "accuracy": 0.1009,
    "loss": 2.302487850189209
  },
  {
    "round": 189,
    "accuracy": 0.0982,
    "loss": 2.3025500774383545
  },
  {
    "round": 190,
    "accuracy": 0.098,
    "loss": 2.3026137351989746
  },
  {
    "round": 191,
    "accuracy": 0.0892,
    "loss": 2.303250551223755
  },
  {
    "round": 192,
    "accuracy": 0.1028,
    "loss": 2.303133726119995
  },
  {
    "round": 193,
    "accuracy": 0.1032,
    "loss": 2.30298113822937
  },
  {
    "round": 194,
    "accuracy": 0.1135,
    "loss": 2.302252769470215
  },
  {
    "round": 195,
    "accuracy": 0.0974,
    "loss": 2.3024017810821533
  },
  {
    "round": 196,
    "accuracy": 0.0958,
    "loss": 2.3026304244995117
  },
  {
    "round": 197,
    "accuracy": 0.101,
    "loss": 2.302561044692993
  },
  {
    "round": 198,
    "accuracy": 0.1009,
    "loss": 2.302485704421997
  },
  {
    "round": 199,
    "accuracy": 0.0982,
    "loss": 2.302549362182617
  },
  {
    "round": 200,
    "accuracy": 0.098,
    "loss": 2.3026156425476074
  }
]